moe_random/__init__.py
moe_random/random.py
moe_random-0.1.8.dist-info/entry_points.txt
moe_random-0.1.8.dist-info/LICENSE
moe_random-0.1.8.dist-info/WHEEL
moe_random-0.1.8.dist-info/METADATA
moe_random-0.1.8.dist-info/RECORD
